AUTHORS.rst
CONTRIBUTING.rst
HISTORY.rst
LICENSE
MANIFEST.in
README.rst
pyproject.toml
setup.py
src/password_security/__init__.py
src/password_security/graph.py
src/password_security/walk_check.py
src/python_password_security.egg-info/PKG-INFO
src/python_password_security.egg-info/SOURCES.txt
src/python_password_security.egg-info/dependency_links.txt
src/python_password_security.egg-info/requires.txt
src/python_password_security.egg-info/top_level.txt