Metadata-Version: 2.1
Name: python-password-security
Version: 1.0.1
Summary: Checks the security of the password based on NSA Network Infrastructure Guidelines
Author-email: Aria Bagheri <ariab9342@gmail.com>
License: MIT License
Project-URL: Homepage, https://github.com/AriaBagheri/python_password_security
Keywords: python,security,password,keyboard walks,dictionary attack
Classifier: License :: OSI Approved :: MIT License
Classifier: Programming Language :: Python
Classifier: Programming Language :: Python :: 3
Requires-Python: >=3.9
License-File: LICENSE
License-File: AUTHORS.rst
